{"lastUsed":1666076063749,"path":"C:\/Attendence management system","projectCount":1,"recentFiles":[{"path":"\/AttendenceManagementService","parentWorkspace":"C:\/Attendence management system","name":"pom.xml","lastModified":1665646349424,"locationURI":"file:\/C:\/Attendence%20management%20system\/AttendenceManagementService\/pom.xml"},{"path":"\/AttendenceManagementService\/src\/main\/resources","parentWorkspace":"C:\/Attendence management system","name":"application.properties","lastModified":1666076063750,"locationURI":"file:\/C:\/Attendence%20management%20system\/AttendenceManagementService\/src\/main\/resources\/application.properties"}]}